neuralib/atlas/__init__.py
neuralib/atlas/data.py
neuralib/atlas/map.py
neuralib/atlas/plot.py
neuralib/atlas/typing.py
neuralib/atlas/util.py
neuralib/atlas/view.py
neuralib/atlas/brainrender/__init__.py
neuralib/atlas/brainrender/core.py
neuralib/atlas/brainrender/main_app.py
neuralib/atlas/brainrender/probe.py
neuralib/atlas/brainrender/roi.py
neuralib/atlas/brainrender/util.py
neuralib/atlas/ccf/__init__.py
neuralib/atlas/ccf/dataframe.py
neuralib/atlas/ccf/matrix.py
neuralib/atlas/cellatlas/__init__.py
neuralib/atlas/cellatlas/core.py
neuralib_atlas-0.7.0.dist-info/licenses/LICENSE
neuralib_atlas-0.7.0.dist-info/METADATA
neuralib_atlas-0.7.0.dist-info/WHEEL
neuralib_atlas-0.7.0.dist-info/entry_points.txt
neuralib_atlas-0.7.0.dist-info/top_level.txt
neuralib_atlas-0.7.0.dist-info/RECORD
